[
  {
    "guid": "b812b763-a31d-4d19-bfcc-15b9eac432cb",
    "name": "Subtitles Tools",
    "description": "通过 subtitles-tools Python 服务为 Jellyfin 提供远程字幕搜索与下载。",
    "overview": "计算本地视频 CID/GCID，调用 subtitles-tools 服务搜索迅雷字幕，并以 Jellyfin 原生字幕提供器方式展示与下载。",
    "owner": "yexi-by",
    "category": "Metadata",
    "repositoryUrl": "https://github.com/yexi-by/jellyfin-plugin-subtitles-tools",
    "repositoryName": "yexi-by/jellyfin-plugin-subtitles-tools",
    "versions": [
      {
        "version": "0.2.0.0",
        "changelog": "新增视频哈希预计算能力：可在配置页开启新增媒体自动预计算，并新增手动计划任务补算缺失 GCID/CID；同时保留可配置并发数，默认 1。",
        "targetAbi": "10.11.0.0",
        "sourceUrl": "https://github.com/yexi-by/jellyfin-plugin-subtitles-tools/releases/download/v0.2.0.0/Jellyfin.Plugin.SubtitlesTools_0.2.0.0.zip",
        "checksum": "A4B743F2C708F8904C824A78BFDAD710",
        "timestamp": "2026-03-20T15:42:05Z"
      }
    ]
  }
]
